README.rst
setup.py
kimono/__init__.py
kimono/kimono.py
kimono.egg-info/PKG-INFO
kimono.egg-info/SOURCES.txt
kimono.egg-info/dependency_links.txt
kimono.egg-info/not-zip-safe
kimono.egg-info/requires.txt
kimono.egg-info/top_level.txt