Metadata-Version: 1.0
Name: kimono
Version: 0.2.3
Summary: Python wrapper for kimonolabs API
Home-page: https://github.com/vu3jej/kimono
Author: Jithesh E J
Author-email: mail@jithesh.net
License: MIT
Platform: UNKNOWN
